[
  {
    "ContainingType": "CreativePeak.API.Controllers.AuthController",
    "Method": "Login",
    "RelativePath": "api/Auth/Login",
    "HttpMethod": "POST",
    "IsController": true,
    "Order": 0,
    "Parameters": [
      {
        "Name": "loginModel",
        "Type": "CreativePeak.Core.PostModels.LoginModel",
        "IsRequired": true
      }
    ],
    "ReturnTypes": []
  },
  {
    "ContainingType": "CreativePeak.API.Controllers.AuthController",
    "Method": "Register",
    "RelativePath": "api/Auth/Register",
    "HttpMethod": "POST",
    "IsController": true,
    "Order": 0,
    "Parameters": [
      {
        "Name": "userPostModel",
        "Type": "CreativePeak.Core.PostModels.UserPostModel",
        "IsRequired": true
      }
    ],
    "ReturnTypes": []
  },
  {
    "ContainingType": "CreativePeak.API.Controllers.CategoryController",
    "Method": "Get",
    "RelativePath": "api/Category",
    "HttpMethod": "GET",
    "IsController": true,
    "Order": 0,
    "Parameters": [],
    "ReturnTypes": []
  },
  {
    "ContainingType": "CreativePeak.API.Controllers.CategoryController",
    "Method": "Post",
    "RelativePath": "api/Category",
    "HttpMethod": "POST",
    "IsController": true,
    "Order": 0,
    "Parameters": [
      {
        "Name": "category",
        "Type": "CreativePeak.Core.PostModels.CategoryPostModel",
        "IsRequired": true
      }
    ],
    "ReturnTypes": []
  },
  {
    "ContainingType": "CreativePeak.API.Controllers.CategoryController",
    "Method": "Get",
    "RelativePath": "api/Category/{id}",
    "HttpMethod": "GET",
    "IsController": true,
    "Order": 0,
    "Parameters": [
      {
        "Name": "id",
        "Type": "System.Int32",
        "IsRequired": true
      }
    ],
    "ReturnTypes": []
  },
  {
    "ContainingType": "CreativePeak.API.Controllers.CategoryController",
    "Method": "Put",
    "RelativePath": "api/Category/{id}",
    "HttpMethod": "PUT",
    "IsController": true,
    "Order": 0,
    "Parameters": [
      {
        "Name": "id",
        "Type": "System.Int32",
        "IsRequired": true
      },
      {
        "Name": "category",
        "Type": "CreativePeak.Core.PostModels.CategoryPostModel",
        "IsRequired": true
      }
    ],
    "ReturnTypes": []
  },
  {
    "ContainingType": "CreativePeak.API.Controllers.CategoryController",
    "Method": "Delete",
    "RelativePath": "api/Category/{id}",
    "HttpMethod": "DELETE",
    "IsController": true,
    "Order": 0,
    "Parameters": [
      {
        "Name": "id",
        "Type": "System.Int32",
        "IsRequired": true
      }
    ],
    "ReturnTypes": []
  },
  {
    "ContainingType": "CreativePeak.API.Controllers.DesignerDetailsController",
    "Method": "Get",
    "RelativePath": "api/DesignerDetails",
    "HttpMethod": "GET",
    "IsController": true,
    "Order": 0,
    "Parameters": [],
    "ReturnTypes": []
  },
  {
    "ContainingType": "CreativePeak.API.Controllers.DesignerDetailsController",
    "Method": "Post",
    "RelativePath": "api/DesignerDetails",
    "HttpMethod": "POST",
    "IsController": true,
    "Order": 0,
    "Parameters": [
      {
        "Name": "designerDetails",
        "Type": "CreativePeak.Core.PostModels.DesignerDetailsPostModel",
        "IsRequired": true
      }
    ],
    "ReturnTypes": []
  },
  {
    "ContainingType": "CreativePeak.API.Controllers.DesignerDetailsController",
    "Method": "Get",
    "RelativePath": "api/DesignerDetails/{id}",
    "HttpMethod": "GET",
    "IsController": true,
    "Order": 0,
    "Parameters": [
      {
        "Name": "id",
        "Type": "System.Int32",
        "IsRequired": true
      }
    ],
    "ReturnTypes": []
  },
  {
    "ContainingType": "CreativePeak.API.Controllers.DesignerDetailsController",
    "Method": "Put",
    "RelativePath": "api/DesignerDetails/{id}",
    "HttpMethod": "PUT",
    "IsController": true,
    "Order": 0,
    "Parameters": [
      {
        "Name": "id",
        "Type": "System.Int32",
        "IsRequired": true
      },
      {
        "Name": "designerDetails",
        "Type": "CreativePeak.Core.PostModels.DesignerDetailsPostModel",
        "IsRequired": true
      }
    ],
    "ReturnTypes": []
  },
  {
    "ContainingType": "CreativePeak.API.Controllers.DesignerDetailsController",
    "Method": "Delete",
    "RelativePath": "api/DesignerDetails/{id}",
    "HttpMethod": "DELETE",
    "IsController": true,
    "Order": 0,
    "Parameters": [
      {
        "Name": "id",
        "Type": "System.Int32",
        "IsRequired": true
      }
    ],
    "ReturnTypes": []
  },
  {
    "ContainingType": "CreativePeak.API.Controllers.ImageController",
    "Method": "Get",
    "RelativePath": "api/Image",
    "HttpMethod": "GET",
    "IsController": true,
    "Order": 0,
    "Parameters": [],
    "ReturnTypes": []
  },
  {
    "ContainingType": "CreativePeak.API.Controllers.ImageController",
    "Method": "Post",
    "RelativePath": "api/Image",
    "HttpMethod": "POST",
    "IsController": true,
    "Order": 0,
    "Parameters": [
      {
        "Name": "image",
        "Type": "CreativePeak.Core.PostModels.ImagePostModel",
        "IsRequired": true
      }
    ],
    "ReturnTypes": []
  },
  {
    "ContainingType": "CreativePeak.API.Controllers.ImageController",
    "Method": "GetByIdAsync",
    "RelativePath": "api/Image/{id}",
    "HttpMethod": "GET",
    "IsController": true,
    "Order": 0,
    "Parameters": [
      {
        "Name": "id",
        "Type": "System.Int32",
        "IsRequired": true
      }
    ],
    "ReturnTypes": []
  },
  {
    "ContainingType": "CreativePeak.API.Controllers.ImageController",
    "Method": "Put",
    "RelativePath": "api/Image/{id}",
    "HttpMethod": "PUT",
    "IsController": true,
    "Order": 0,
    "Parameters": [
      {
        "Name": "id",
        "Type": "System.Int32",
        "IsRequired": true
      },
      {
        "Name": "image",
        "Type": "CreativePeak.Core.PostModels.ImagePostModel",
        "IsRequired": true
      }
    ],
    "ReturnTypes": []
  },
  {
    "ContainingType": "CreativePeak.API.Controllers.ImageController",
    "Method": "Delete",
    "RelativePath": "api/Image/{id}",
    "HttpMethod": "DELETE",
    "IsController": true,
    "Order": 0,
    "Parameters": [
      {
        "Name": "id",
        "Type": "System.Int32",
        "IsRequired": true
      }
    ],
    "ReturnTypes": []
  },
  {
    "ContainingType": "CreativePeak.API.Controllers.S3ImagesController",
    "Method": "GetPresignedUrl",
    "RelativePath": "api/S3Images/image-url",
    "HttpMethod": "GET",
    "IsController": true,
    "Order": 0,
    "Parameters": [
      {
        "Name": "fileName",
        "Type": "System.String",
        "IsRequired": false
      }
    ],
    "ReturnTypes": []
  },
  {
    "ContainingType": "CreativePeak.API.Controllers.UserController",
    "Method": "Get",
    "RelativePath": "api/User",
    "HttpMethod": "GET",
    "IsController": true,
    "Order": 0,
    "Parameters": [],
    "ReturnTypes": []
  },
  {
    "ContainingType": "CreativePeak.API.Controllers.UserController",
    "Method": "Post",
    "RelativePath": "api/User",
    "HttpMethod": "POST",
    "IsController": true,
    "Order": 0,
    "Parameters": [
      {
        "Name": "user",
        "Type": "CreativePeak.Core.PostModels.UserPostModel",
        "IsRequired": true
      }
    ],
    "ReturnTypes": []
  },
  {
    "ContainingType": "CreativePeak.API.Controllers.UserController",
    "Method": "Get",
    "RelativePath": "api/User/{id}",
    "HttpMethod": "GET",
    "IsController": true,
    "Order": 0,
    "Parameters": [
      {
        "Name": "id",
        "Type": "System.Int32",
        "IsRequired": true
      }
    ],
    "ReturnTypes": []
  },
  {
    "ContainingType": "CreativePeak.API.Controllers.UserController",
    "Method": "UpdateWithPassword",
    "RelativePath": "api/User/{id}",
    "HttpMethod": "PUT",
    "IsController": true,
    "Order": 0,
    "Parameters": [
      {
        "Name": "id",
        "Type": "System.Int32",
        "IsRequired": true
      },
      {
        "Name": "user",
        "Type": "CreativePeak.Core.PostModels.UserPostModel",
        "IsRequired": true
      }
    ],
    "ReturnTypes": []
  },
  {
    "ContainingType": "CreativePeak.API.Controllers.UserController",
    "Method": "Delete",
    "RelativePath": "api/User/{id}",
    "HttpMethod": "DELETE",
    "IsController": true,
    "Order": 0,
    "Parameters": [
      {
        "Name": "id",
        "Type": "System.Int32",
        "IsRequired": true
      }
    ],
    "ReturnTypes": []
  },
  {
    "ContainingType": "CreativePeak.API.Controllers.UserController",
    "Method": "UpdateWithoutPassword",
    "RelativePath": "api/User/updateWithoutPassword/{id}",
    "HttpMethod": "PUT",
    "IsController": true,
    "Order": 0,
    "Parameters": [
      {
        "Name": "id",
        "Type": "System.Int32",
        "IsRequired": true
      },
      {
        "Name": "user",
        "Type": "CreativePeak.Core.PostModels.UserWithoutPasswordPostModel",
        "IsRequired": true
      }
    ],
    "ReturnTypes": []
  }
]